gdmec23120139/__init__.py
gdmec23120139-0.1.0.dist-info/METADATA
gdmec23120139-0.1.0.dist-info/WHEEL
gdmec23120139-0.1.0.dist-info/entry_points.txt
gdmec23120139-0.1.0.dist-info/RECORD
